pyvals/__init__.py
PyVals-1.2.2.dist-info/LICENCE.txt
PyVals-1.2.2.dist-info/METADATA
PyVals-1.2.2.dist-info/WHEEL
PyVals-1.2.2.dist-info/top_level.txt
PyVals-1.2.2.dist-info/RECORD
