Metadata-Version: 2.1
Name: PyVals
Version: 1.2.2
Summary: Easily import and export values into python
Home-page: UNKNOWN
Author: Xyndra
Author-email: xyndra@deutschergamingserver.de
License: MIT License
Platform: UNKNOWN
Classifier: Development Status :: 1 - Planning
Classifier: License :: OSI Approved :: MIT License
Classifier: Operating System :: OS Independent
Classifier: Programming Language :: Python :: 3.10
Classifier: Typing :: Typed
License-File: LICENCE.txt
